pynchmark/__init__.py
pynchmark/pynchmark.py
pynchmark-0.0.4.dist-info/METADATA
pynchmark-0.0.4.dist-info/WHEEL
pynchmark-0.0.4.dist-info/entry_points.txt
pynchmark-0.0.4.dist-info/RECORD
