Metadata-Version: 2.1
Name: pynchmark
Version: 0.0.4
Summary: 
Author: Simon Delamare
Author-email: simon.delamare@ens-lyon.fr
Requires-Python: >3.9
Classifier: Programming Language :: Python :: 3
Classifier: Programming Language :: Python :: 3.10
Classifier: Programming Language :: Python :: 3.11
Classifier: Programming Language :: Python :: 3.12
Requires-Dist: matplotlib (>3.9)
Requires-Dist: numpy (>2)
Requires-Dist: pandas (>2.2)
Requires-Dist: psutil (>=6.0.0,<7.0.0)
Requires-Dist: pyonf (>=0.3,<0.4)
Requires-Dist: seaborn (>0.13)
